.travis.yml
AUTHORS
ChangeLog
README.rst
requirements.txt
setup.cfg
setup.py
test-requirements.txt
myr/__init__.py
myr.base.egg-info/PKG-INFO
myr.base.egg-info/SOURCES.txt
myr.base.egg-info/dependency_links.txt
myr.base.egg-info/namespace_packages.txt
myr.base.egg-info/not-zip-safe
myr.base.egg-info/pbr.json
myr.base.egg-info/requires.txt
myr.base.egg-info/top_level.txt
myr/base/__init__.py
myr/base/app.py
tests/__init__.py
tests/test_base.py