Metadata-Version: 1.1
Name: myr.base
Version: 0.1.0
Summary: Auto-announce Celery-based tasks
Home-page: https://github.com/Vnet-as/myr-base
Author: Vnet a.s.
Author-email: sap@vnet.sk
License: MIT
Keywords: rpc
Platform: UNKNOWN
Classifier: Development Status :: 4 - Beta
Classifier: Environment :: Console
Classifier: Intended Audience :: Developers
Classifier: Intended Audience :: Information Technology
Classifier: License :: OSI Approved :: MIT License
Classifier: Operating System :: OS Independent
Classifier: Programming Language :: Python
